pip/_internal/self_outdated_check.py
wheelofdespair-0.0.1.dist-info/METADATA
wheelofdespair-0.0.1.dist-info/WHEEL
wheelofdespair-0.0.1.dist-info/top_level.txt
wheelofdespair-0.0.1.dist-info/RECORD
